extra_streamlit_components/__init__.py
extra_streamlit_components/BouncingImage/__init__.py
extra_streamlit_components/BouncingImage/frontend/build/asset-manifest.json
extra_streamlit_components/BouncingImage/frontend/build/bootstrap.min.css
extra_streamlit_components/BouncingImage/frontend/build/index.html
extra_streamlit_components/BouncingImage/frontend/build/precache-manifest.96984c5ce94de38f653778d605818848.js
extra_streamlit_components/BouncingImage/frontend/build/service-worker.js
extra_streamlit_components/BouncingImage/frontend/build/static/js/2.bb34b22f.chunk.js
extra_streamlit_components/BouncingImage/frontend/build/static/js/2.bb34b22f.chunk.js.LICENSE.txt
extra_streamlit_components/BouncingImage/frontend/build/static/js/2.bb34b22f.chunk.js.map
extra_streamlit_components/BouncingImage/frontend/build/static/js/main.c3db22c1.chunk.js
extra_streamlit_components/BouncingImage/frontend/build/static/js/main.c3db22c1.chunk.js.map
extra_streamlit_components/BouncingImage/frontend/build/static/js/runtime-main.fb6bf013.js
extra_streamlit_components/BouncingImage/frontend/build/static/js/runtime-main.fb6bf013.js.map
extra_streamlit_components/CookieManager/__init__.py
extra_streamlit_components/CookieManager/frontend/build/asset-manifest.json
extra_streamlit_components/CookieManager/frontend/build/bootstrap.min.css
extra_streamlit_components/CookieManager/frontend/build/index.html
extra_streamlit_components/CookieManager/frontend/build/static/js/2.23c6e063.chunk.js
extra_streamlit_components/CookieManager/frontend/build/static/js/2.23c6e063.chunk.js.LICENSE.txt
extra_streamlit_components/CookieManager/frontend/build/static/js/2.23c6e063.chunk.js.map
extra_streamlit_components/CookieManager/frontend/build/static/js/main.f28005a3.chunk.js
extra_streamlit_components/CookieManager/frontend/build/static/js/main.f28005a3.chunk.js.map
extra_streamlit_components/CookieManager/frontend/build/static/js/runtime-main.5b9a054e.js
extra_streamlit_components-0.1.81.dist-info/LICENSE
extra_streamlit_components-0.1.81.dist-info/METADATA
extra_streamlit_components-0.1.81.dist-info/WHEEL
extra_streamlit_components-0.1.81.dist-info/top_level.txt
extra_streamlit_components-0.1.81.dist-info/RECORD
