Metadata-Version: 2.1
Name: extra-streamlit-components
Version: 0.1.81
Summary: An all-in-one place, to find complex or just natively unavailable components on streamlit.
Home-page: https://github.com/Mohamed-512/Extra-Streamlit-Components
Author: Mohamed Abdou
Author-email: matex512@gmail.com
License: UNKNOWN
Keywords: Python,Streamlit,React,JavaScript
Platform: UNKNOWN
Classifier: Programming Language :: Python :: 3
Classifier: License :: OSI Approved :: MIT License
Classifier: Operating System :: OS Independent
Requires-Python: >=3.6
